{
"type": "FeatureCollection",
"name": "Study Spot JSON",
"crs": { "type": "name", "properties": { "name": "urn:ogc:def:crs:OGC:1.3:CRS84" } },
"features": [
{ "type": "Feature", "properties": { "id": 2 }, "geometry": { "type": "Point", "coordinates": [ -79.051189038164665, 35.911309785827328 ] } }
]
}
